setup.py
src/sfutools/__init__.py
src/sfutools/sfutools.py
src/sfutools.egg-info/PKG-INFO
src/sfutools.egg-info/SOURCES.txt
src/sfutools.egg-info/dependency_links.txt
src/sfutools.egg-info/top_level.txt