Metadata-Version: 1.1
Name: sfutools
Version: 1.0
Summary: Some simple, fast, and useful tools help you programming(Maybe).
Home-page: UNKNOWN
Author: eternalbluephy
Author-email: UNKNOWN
License: UNKNOWN
Platform: UNKNOWN
Classifier: Intended Audience :: Developers
Classifier: Operating System :: OS Independent
Classifier: Natural Language :: English
Classifier: Programming Language :: Python
Classifier: Programming Language :: Python :: 3
Classifier: Topic :: Utilities
